{
  "Symbol": "CL",
  "Sharpe": 0.9806331181362296,
  "Deflated_Sharpe": null,
  "Profit_Factor": 1.5534960403834577,
  "Trades": 4243,
  "Prod_Threshold": 0.6,
  "Guardrails": {
    "Trades": 500,
    "Era_Positive_Count": 4,
    "Era_Count": 5
  },
  "Params": {
    "n_estimators": 900,
    "min_samples_leaf": 200,
    "max_depth": 3,
    "max_features": "log2",
    "bootstrap": true,
    "max_samples": 0.8318001331390404,
    "class_weight": null,
    "n_jobs": -1,
    "random_state": 42
  },
  "Features": [
    "6c_hourly_return",
    "es_hourly_return",
    "ym_hourly_return",
    "6a_hourly_return",
    "rty_hourly_return",
    "nq_hourly_return",
    "6m_hourly_return",
    "6a_hourly_z_score",
    "6c_hourly_z_score",
    "ym_hourly_z_score",
    "6e_hourly_return",
    "6b_hourly_return",
    "rty_hourly_z_score",
    "es_hourly_z_score",
    "6n_hourly_return",
    "6m_hourly_z_score",
    "donchian_proximity_to_nearest_band",
    "6s_hourly_return",
    "hourly_atr_percentile",
    "prev_bar_pct",
    "6j_hourly_return",
    "donchian_proximity_daily_to_nearest_band",
    "6e_hourly_z_score",
    "nq_hourly_z_score",
    "prev_bar_pct_pct",
    "ng_hourly_return_pipeline",
    "cl_hourly_return",
    "volz_pct",
    "daily_rsi_len_14"
  ],
  "Score_Metric": "Sharpe"
}